flasktut/__init__.py
flasktut-0.0.1.dist-info/LICENSE.rst
flasktut-0.0.1.dist-info/METADATA
flasktut-0.0.1.dist-info/WHEEL
flasktut-0.0.1.dist-info/top_level.txt
flasktut-0.0.1.dist-info/RECORD
