Metadata-Version: 2.1
Name: flasktut
Version: 0.0.1
Summary: The basic app.
Home-page: https://flask.palletsprojects.com/tutorial/
Maintainer: Pallets
Maintainer-email: contact@palletsprojects.com
License: BSD-3-Clause
Platform: UNKNOWN
License-File: LICENSE.rst
Requires-Dist: Flask
Provides-Extra: test
Requires-Dist: pytest ; extra == 'test'
